minsnap_trajectories/__init__.py
minsnap_trajectories/minimum_snap.py
minsnap_trajectories/minimum_snap.pyi
minsnap_trajectories-0.1.1.dist-info/LICENSE
minsnap_trajectories-0.1.1.dist-info/METADATA
minsnap_trajectories-0.1.1.dist-info/WHEEL
minsnap_trajectories-0.1.1.dist-info/top_level.txt
minsnap_trajectories-0.1.1.dist-info/RECORD
