Metadata-Version: 2.1
Name: minsnap_trajectories
Version: 0.1.1
Summary: Simple minimum-snap trajectory generator
Author-email: H S Helson Go <hei.go@mail.utoronto.ca>
License: MIT
Project-URL: Homepage, https://github.com/Hs293Go/minsnap_trajectories
Keywords: trajectory generation,path planning,minimum snap,differential flatness
Classifier: Programming Language :: Python :: 3
Classifier: License :: OSI Approved :: MIT License
Classifier: Operating System :: OS Independent
Requires-Python: >=3.8
License-File: LICENSE
Requires-Dist: numpy
Requires-Dist: scipy
Provides-Extra: dev
Requires-Dist: pytest ; extra == 'dev'
Requires-Dist: black ; extra == 'dev'
Requires-Dist: isort ; extra == 'dev'
